odoo/addons/website_recaptcha_reloaded/__init__.py
odoo/addons/website_recaptcha_reloaded/__manifest__.py
odoo/addons/website_recaptcha_reloaded/website.py
odoo/addons/website_recaptcha_reloaded/models/__init__.py
odoo/addons/website_recaptcha_reloaded/models/res_config.py
odoo/addons/website_recaptcha_reloaded/static/description/icon.png
odoo/addons/website_recaptcha_reloaded/static/description/index.html
odoo/addons/website_recaptcha_reloaded/static/description/recaptcha_setting.png
odoo/addons/website_recaptcha_reloaded/views/res_config.xml
odoo/addons/website_recaptcha_reloaded/views/website_view.xml
odoo12_addon_website_recaptcha_reloaded-12.0.0.1.0.99.dev1.dist-info/METADATA
odoo12_addon_website_recaptcha_reloaded-12.0.0.1.0.99.dev1.dist-info/WHEEL
odoo12_addon_website_recaptcha_reloaded-12.0.0.1.0.99.dev1.dist-info/top_level.txt
odoo12_addon_website_recaptcha_reloaded-12.0.0.1.0.99.dev1.dist-info/RECORD
