Metadata-Version: 2.1
Name: odoo12-addon-website-recaptcha-reloaded
Version: 12.0.0.1.0.99.dev1
Summary: Website reCAPTCHA Reloaded
Home-page: https://www.techreceptives.com
Author: Tech Receptives
License: AGPL-3
Platform: UNKNOWN
Classifier: Programming Language :: Python
Classifier: Framework :: Odoo
Classifier: License :: OSI Approved :: GNU Affero General Public License v3
Requires-Python: >=3.5
Requires-Dist: odoo (<12.1dev,>=12.0a)
